{
  "Data Link": {
    "Host": "192.168.1.143",
    "Port": 52020
  },
  "ASI Learjet": {
    "Enabled": false,
    "Position X": 562,
    "Position Y": 20,
    "Size": 280
  },
  "ADI Learjet": {
    "Enabled": false,
    "Position X": 882,
    "Position Y": 10,
    "Size": 300
  },
  "ALT Learjet": {
    "Enabled": false,
    "Position X": 1222,
    "Position Y": 20,
    "Size": 280
  },
  "ASI": {
    "Enabled": true,
    "Position X": 565,
    "Position Y": 15,
    "Size": 280
  },
  "ADI": {
    "Enabled": true,
    "Position X": 882,
    "Position Y": 7,
    "Size": 290
  },
  "ALT": {
    "Enabled": true,
    "Position X": 1222,
    "Position Y": 13,
    "Size": 275
  },
  "VOR1": {
    "Enabled": true,
    "Position X": 1543,
    "Position Y": 10,
    "Size": 280
  },
  "TC": {
    "Enabled": true,
    "Position X": 562,
    "Position Y": 342,
    "Size": 280
  },
  "HI": {
    "Enabled": true,
    "Position X": 892,
    "Position Y": 345,
    "Size": 274
  },
  "VSI": {
    "Enabled": true,
    "Position X": 1219,
    "Position Y": 342,
    "Size": 284
  },
  "VOR2": {
    "Enabled": true,
    "Position X": 1543,
    "Position Y": 342,
    "Size": 280
  },
  "Trim Flaps": {
    "Enabled": true,
    "Position X": 885,
    "Position Y": 676,
    "Size": 280
  },
  "RPM": {
    "Enabled": true,
    "Position X": 1217,
    "Position Y": 674,
    "Size": 284
  },
  "ADF": {
    "Enabled": true,
    "Position X": 1543,
    "Position Y": 676,
    "Size": 280
  },
  "Annunciator": {
    "Enabled": true,
    "Position X": 135,
    "Position Y": 20,
    "Size": 300
  },
  "Digital Clock": {
    "Enabled": true,
    "Position X": 312,
    "Position Y": 135,
    "Size": 200
  },
  "Fuel": {
    "Enabled": true,
    "Position X": 72,
    "Position Y": 375,
    "Size": 200
  },
  "EGT": {
    "Enabled": true,
    "Position X": 312,
    "Position Y": 375,
    "Size": 200
  },
  "VAC": {
    "Enabled": true,
    "Position X": 72,
    "Position Y": 615,
    "Size": 200
  },
  "Oil": {
    "Enabled": true,
    "Position X": 312,
    "Position Y": 615,
    "Size": 200
  },
  "Nav": {
    "Enabled": true,
    "Position X": 72,
    "Position Y": 855,
    "Size": 600
  }
}
